eplot/__init__.py
eplot/eplot.py
eplot-0.1.2.dist-info/DESCRIPTION.rst
eplot-0.1.2.dist-info/METADATA
eplot-0.1.2.dist-info/RECORD
eplot-0.1.2.dist-info/WHEEL
eplot-0.1.2.dist-info/metadata.json
eplot-0.1.2.dist-info/top_level.txt
