Metadata-Version: 2.0
Name: eplot
Version: 0.1.2
Summary: pandas interface for pyecharts
Home-page: https://github.com/pjgao/eplot
Author: pipixiu
Author-email: 1783198484@qq.com
License: UNKNOWN
Platform: UNKNOWN
Classifier: Programming Language :: Python :: 3
Classifier: License :: OSI Approved :: MIT License
Classifier: Operating System :: OS Independent
Requires-Dist: numpy
Requires-Dist: pandas
Requires-Dist: pyecharts
